Metadata-Version: 1.1
Name: stellar-p2p
Version: 0.4.4rc0
Summary: stellar-p2p is a modified version of stellar, a tool for creating and restoring database snapshots
Home-page: https://github.com/craftypenguins/stellar-p2p
Author: Rob Hartzenberg
Author-email: rob@hartzenberg.net
License: BSD
Platform: any
Classifier: Intended Audience :: Developers
Classifier: License :: OSI Approved :: BSD License
Classifier: Operating System :: POSIX
Classifier: Operating System :: Microsoft :: Windows
Classifier: Operating System :: MacOS :: MacOS X
Classifier: Topic :: Utilities
Classifier: Programming Language :: Python :: 2
Classifier: Programming Language :: Python :: 3
Classifier: Topic :: Database
Classifier: Topic :: Software Development :: Version Control
